quantumcarrot/__init__.py
quantumcarrot/quantumcarrot.py
quantumcarrot-1.0.0.dist-info/LICENSE.txt
quantumcarrot-1.0.0.dist-info/METADATA
quantumcarrot-1.0.0.dist-info/WHEEL
quantumcarrot-1.0.0.dist-info/top_level.txt
quantumcarrot-1.0.0.dist-info/RECORD
