Metadata-Version: 2.1
Name: quantumcarrot
Version: 1.0.0
Summary: QUANTUMCARROT
Author: David Huang Peterson
Author-email: holypenguin.david@gmail.com
Classifier: Programming Language :: Python :: 3
Classifier: License :: OSI Approved :: MIT License
Classifier: Operating System :: OS Independent
License-File: LICENSE.txt
